{
    "status": "success",
    "data": {
        "stats": {
            "total": 47830,
            "totalCoins": 47830,
            "totalMarkets": 44644,
            "totalExchanges": 187,
            "totalMarketCap": "944",
            "total24hVolume": "139211434488"
        },
        "coins": [
            {
                "uuid": "Qwsogvtv82FCd",
                "symbol": "BTC",
                "name": "Bitcoin",
                "color": "#f7931A",
                "iconUrl": "https://cdn.coinranking.com/bOabBYkcX/bitcoin_btc.svg",
                "marketCap": "2087569662915",
                "price": "105357.65081300662",
                "listedAt": 1330214400,
                "tier": 1,
                "change": "1.04",
                "rank": 1,
                "sparkline": [
                    "104253.43397513368",
                    "104374.52683225092",
                    "104467.423744293",
                    "104442.60638365208",
                    "104003.76666206574",
                    "104090.74331600471",
                    "103898.53814316125",
                    "103472.98815535223",
                    "103247.28127011516",
                    "102464.11078984044",
                    "102811.78455510053",
                    "102039.35963246008",
                    "102240.68229621823",
                    "102663.83281983687",
                    "102405.36750129735",
                    "102421.78967914013",
                    "102145.20433303853",
                    "101733.82551123401",
                    "101935.11449420238",
                    "101715.0840753511",
                    "101848.85667808456",
                    "103434.67952330744",
                    "104474.35194873864",
                    null
                ],
                "lowVolume": false,
                "coinrankingUrl": "https://coinranking.com/coin/Qwsogvtv82FCd+bitcoin-btc",
                "24hVolume": "67279575187",
                "btcPrice": "1",
                "contractAddresses": []
            },
            {
                "uuid": "razxDUgYGNAdQ",
                "symbol": "ETH",
                "name": "Ethereum",
                "color": "#3C3C3D",
                "iconUrl": "https://cdn.coinranking.com/rk4RKHOuW/eth.svg",
                "marketCap": "391527546399",
                "price": "3249.103145488752",
                "listedAt": 1438905600,
                "tier": 1,
                "change": "-0.92",
                "rank": 2,
                "sparkline": [
                    "3281.7593584756955",
                    "3274.4919939364413",
                    "3265.8872027006555",
                    "3265.9375094426364",
                    "3253.361246245045",
                    "3254.8233043161067",
                    "3240.084956317313",
                    "3250.783458187368",
                    "3246.4249083992286",
                    "3219.90662556587",
                    "3232.9144663928855",
                    "3211.7716957391835",
                    "3209.9096211156952",
                    "3215.7947994664555",
                    "3216.53858700668",
                    "3223.193327462861",
                    "3211.077867892366",
                    "3200.8017693995585",
                    "3207.3206383393895",
                    "3204.7315604532423",
                    "3217.9122567381164",
                    "3247.7069534676602",
                    "3252.2442505922145",
                    null
                ],
                "lowVolume": false,
                "coinrankingUrl": "https://coinranking.com/coin/razxDUgYGNAdQ+ethereum-eth",
                "24hVolume": "19465624866",
                "btcPrice": "0.03083879642737482",
                "contractAddresses": []
            },
            {
                "uuid": "-l8Mn2pVlRs-p",
                "symbol": "XRP",
                "name": "XRP",
                "color": "#000000",
                "iconUrl": "https://cdn.coinranking.com/B1oPuTyfX/xrp.svg",
                "marketCap": "179720162493",
                "price": "3.122069051085176",
                "listedAt": 1421798400,
                "tier": 1,
                "change": "-1.86",
                "rank": 3,
                "sparkline": [
                    "3.1836597645135365",
                    "3.18555140193792",
                    "3.201099165500195",
                    "3.256025811092076",
                    "3.197507845392884",
                    "3.1821656700671315",
                    "3.17786332324907",
                    "3.1794276197000704",
                    "3.170668799299427",
                    "3.147384409396771",
                    "3.165354957529332",
                    "3.142374323372249",
                    "3.137674649679203",
                    "3.14513896842687",
                    "3.128410461207501",
                    "3.1243622339949773",
                    "3.108078374347351",
                    "3.0933406582827847",
                    "3.0821150139803692",
                    "3.0648149790320733",
                    "3.064431898917002",
                    "3.1150917452927667",
                    "3.1299286341249326",
                    null
                ],
                "lowVolume": false,
                "coinrankingUrl": "https://coinranking.com/coin/-l8Mn2pVlRs-p+xrp-xrp",
                "24hVolume": "6219340591",
                "btcPrice": "0.000029633054903876",
                "contractAddresses": []
            },
            {
                "uuid": "HIVsRcGKkPFtW",
                "symbol": "USDT",
                "name": "Tether USD",
                "color": "#22a079",
                "iconUrl": "https://cdn.coinranking.com/iqfxcAEV1/tether-usd-usdt.svg",
                "marketCap": "138517181113",
                "price": "0.999342466005632",
                "listedAt": 1420761600,
                "tier": 1,
                "change": "-0.06",
                "rank": 4,
                "sparkline": [
                    "0.9999711896817658",
                    "1.000429490295909",
                    "0.999891869077883",
                    "1.0001746524929873",
                    "1.0003128531046679",
                    "1.0002007773222141",
                    "1.0004780277509333",
                    "1.0001295088303297",
                    "1.0002008822841972",
                    "1.000229583442364",
                    "1.0001316254467187",
                    "1.0003695839846931",
                    "0.99978773297364",
                    "1.000165862622895",
                    "0.9999522210998986",
                    "1.0002555771337522",
                    "1.0002377435145033",
                    "0.9999890673492319",
                    "0.9997409506678229",
                    "1.0000250025193114",
                    "0.9995515254516635",
                    "0.9990226774931885",
                    "1.0001449058166783",
                    null
                ],
                "lowVolume": false,
                "coinrankingUrl": "https://coinranking.com/coin/HIVsRcGKkPFtW+tetherusd-usdt",
                "24hVolume": "93462118033",
                "btcPrice": "0.000009485238692151",
                "contractAddresses": [
                    "avalanche-c-chain/0x9702230a8ea53601f5cd2dc00fdbc13d4df4a8c7 ",
                    "tron-trc-20/TR7NHqjeKQxGTCi8q8ZY4pL8otSzgjLj6t",
                    "solana/Es9vMFrzaCERmJfrF4H2FYD4KCoNkY11McCe8BenwNYB",
                    "eos/USDT-eos-tethertether",
                    "omni/31",
                    "bitcoin-cash/9fc89d6b7d5be2eac0b3787c5b8236bca5de641b5bafafc8f450727b63615c11",
                    "liquid/ce091c998b83c78bb71a632313ba3760f1763d9cfcffae02258ffa9865a37bd2",
                    "ethereum/0xdac17f958d2ee523a2206206994597c13d831ec7",
                    "algorand/312769"
                ]
            },
            {
                "uuid": "zNZHO_Sjf",
                "symbol": "SOL",
                "name": "Solana",
                "color": "#000",
                "iconUrl": "https://cdn.coinranking.com/yvUG4Qex5/solana.svg",
                "marketCap": "122460615353",
                "price": "251.67674421300967",
                "listedAt": 1586539320,
                "tier": 1,
                "change": "-3.02",
                "rank": 5,
                "sparkline": [
                    "259.1542348364223",
                    "257.12945644262624",
                    "258.79305999066105",
                    "268.35363962094107",
                    "265.654435228562",
                    "263.10063965911",
                    "257.56144880988404",
                    "256.67787294040426",
                    "255.38877403281518",
                    "249.40543634946073",
                    "249.8935113842467",
                    "247.35003872528108",
                    "248.91514031457743",
                    "249.31281522422407",
                    "248.38369978452732",
                    "248.3076981375026",
                    "247.55177392652448",
                    "245.76338334256425",
                    "244.15519453197447",
                    "243.8169811867792",
                    "244.39336740117412",
                    "248.66533732956918",
                    "248.59646165569578",
                    null
                ],
                "lowVolume": false,
                "coinrankingUrl": "https://coinranking.com/coin/zNZHO_Sjf+solana-sol",
                "24hVolume": "8238474288",
                "btcPrice": "0.002388784699268747",
                "contractAddresses": []
            },
            {
                "uuid": "WcwrkfNI4FUAe",
                "symbol": "BNB",
                "name": "BNB",
                "color": "#e8b342",
                "iconUrl": "https://cdn.coinranking.com/B1N19L_dZ/bnb.svg",
                "marketCap": "103289733193",
                "price": "687.083209669479",
                "listedAt": 1503014400,
                "tier": 1,
                "change": "-1.16",
                "rank": 6,
                "sparkline": [
                    "695.0184210725662",
                    "695.1246938883851",
                    "694.9361744672154",
                    "697.5892524218126",
                    "696.6599046125677",
                    "697.9264259190417",
                    "695.3288125805833",
                    "695.9861249967885",
                    "694.6516421395002",
                    "689.695586911357",
                    "690.7564462204872",
                    "686.6824198852989",
                    "686.3035506767721",
                    "686.2281843891725",
                    "685.9614797444729",
                    "686.9276285555072",
                    "686.3316338536275",
                    "684.3715199161505",
                    "684.7271890691684",
                    "683.6150973190781",
                    "683.594089436238",
                    "687.5157145578808",
                    "687.6853226022766",
                    null
                ],
                "lowVolume": false,
                "coinrankingUrl": "https://coinranking.com/coin/WcwrkfNI4FUAe+bnb-bnb",
                "24hVolume": "725321046",
                "btcPrice": "0.006521436311150714",
                "contractAddresses": ["bnb-beacon-chain/"]
            },
            {
                "uuid": "a91GCGd_u96cF",
                "symbol": "DOGE",
                "name": "Dogecoin",
                "color": "#c2a633",
                "iconUrl": "https://cdn.coinranking.com/H1arXIuOZ/doge.svg",
                "marketCap": "51924906115",
                "price": "0.3528415527026122",
                "listedAt": 1391212800,
                "tier": 1,
                "change": "-2.55",
                "rank": 7,
                "sparkline": [
                    "0.362359384701386",
                    "0.361077536389902",
                    "0.3595184949424142",
                    "0.36129708096114443",
                    "0.35937569194750574",
                    "0.36136942265193495",
                    "0.3620960171155761",
                    "0.36243150812968494",
                    "0.36026069843901604",
                    "0.3548321991201337",
                    "0.3552544393826509",
                    "0.3515321597781729",
                    "0.352141994668484",
                    "0.35423153759519466",
                    "0.35331541010362133",
                    "0.35266383252248895",
                    "0.35122478508103744",
                    "0.34935617172377154",
                    "0.3487871078881105",
                    "0.347307674912944",
                    "0.3478337375848263",
                    "0.3520984970994023",
                    "0.35250409502477026",
                    null
                ],
                "lowVolume": false,
                "coinrankingUrl": "https://coinranking.com/coin/a91GCGd_u96cF+dogecoin-doge",
                "24hVolume": "2536356393",
                "btcPrice": "0.000003348988421627",
                "contractAddresses": []
            },
            {
                "uuid": "aKzUVe4Hh_CON",
                "symbol": "USDC",
                "name": "USDC",
                "color": "#7894b4",
                "iconUrl": "https://cdn.coinranking.com/jkDf8sQbY/usdc.svg",
                "marketCap": "51651822561",
                "price": "0.9994180109719912",
                "listedAt": 1539043200,
                "tier": 1,
                "change": "-0.08",
                "rank": 8,
                "sparkline": [
                    "1.0001457835417171",
                    "1.000502808418471",
                    "1.0004957140324482",
                    "1.000616393497148",
                    "1.0005934781363088",
                    "1.0004554541301351",
                    "1.0006501767341478",
                    "1.0006562510095296",
                    "1.000639573532646",
                    "1.0008617564382334",
                    "1.0007707256556835",
                    "1.0009973793835016",
                    "1.0007024519273005",
                    "1.0006954878930672",
                    "1.0005052887804464",
                    "1.0007791473725467",
                    "1.0006857486240384",
                    "1.0005440373374954",
                    "1.0002254247832791",
                    "1.0004595566070427",
                    "1.00002989261636",
                    "0.9993164652733586",
                    "1.000224025262582",
                    null
                ],
                "lowVolume": false,
                "coinrankingUrl": "https://coinranking.com/coin/aKzUVe4Hh_CON+usdc-usdc",
                "24hVolume": "87168360638",
                "btcPrice": "0.000009485955725663",
                "contractAddresses": [
                    "avalanche-c-chain/0xB97EF9Ef8734C71904D8002F8b6Bc66Dd9c48a6E",
                    "flow/A.b19436aae4d94622.FiatToken",
                    "tron-trc-20/TEkxiTehnzSmSe2XqrBj4w32RUN966rdz8",
                    "stellar/USDC-GA5ZSEJYB37JRC5AVCIA5MOP4RHTM335X2KGX3IHOJAPP5RE34K4KZVN-1",
                    "hedera/0.0.456858",
                    "solana/EPjFWdd5AufqSSqeM2qN1xzybapC8G4wEGGkZwyTDt1v",
                    "moonbeam/0x8f552a71EFE5eeFc207Bf75485b356A0b3f01eC9",
                    "ethereum/0xa0b86991c6218b36c1d19d4a2e9eb0ce3606eb48",
                    "algorand/31566704",
                    "cronos/0xc21223249ca28397b4b6541dffaecc539bff0c59",
                    "klaytn/0x6270b58be569a7c0b8f47594f191631ae5b2c86c",
                    "bnb-smart-chain/0x8ac76a51cc950d9822d68b83fe1ad97b32cd580d",
                    "optimism/0x0b2c639c533813f4aa9d7837caf62653d097ff85",
                    "polygon/0x3c499c542cef5e3811e1192ce70d8cc03d5c3359",
                    "fantom/0x04068da6c83afcfa0e13ba15a6696662335d5b75",
                    "arbitrum/0xaf88d065e77c8cC2239327C5EDb3A432268e5831",
                    "base/0x833589fcd6edb6e08f4c7c32d4f71b54bda02913"
                ]
            },
            {
                "uuid": "qzawljRxB5bYu",
                "symbol": "ADA",
                "name": "Cardano",
                "color": "#3cc8c8",
                "iconUrl": "https://cdn.coinranking.com/ryY28nXhW/ada.svg",
                "marketCap": "37052945854",
                "price": "0.98731027083246",
                "listedAt": 1506902400,
                "tier": 1,
                "change": "-1.27",
                "rank": 9,
                "sparkline": [
                    "1.000689666642063",
                    "0.995006900413531",
                    "0.9925667715460547",
                    "0.9999725692073614",
                    "0.992401713417609",
                    "0.9902312964940312",
                    "0.9826117181392773",
                    "0.9832181933913275",
                    "0.9768836310241903",
                    "0.9671146291684758",
                    "0.9795600626017493",
                    "0.9694132727028395",
                    "0.9691034865639307",
                    "0.9709371586085185",
                    "0.9685484046891144",
                    "0.9692692497949837",
                    "0.9622905236827104",
                    "0.9573384837925364",
                    "0.9598477339402739",
                    "0.9603520328196169",
                    "0.9627802317598663",
                    "0.9788816424341967",
                    "0.9899487767872239",
                    null
                ],
                "lowVolume": false,
                "coinrankingUrl": "https://coinranking.com/coin/qzawljRxB5bYu+cardano-ada",
                "24hVolume": "839865564",
                "btcPrice": "0.000009371035356367",
                "contractAddresses": []
            },
            {
                "uuid": "VINVMYf0u",
                "symbol": "stETH",
                "name": "Lido Staked Ether",
                "color": "#41c0f5",
                "iconUrl": "https://cdn.coinranking.com/UJ-dQdgYY/8085.png",
                "marketCap": "30974817034",
                "price": "3246.451629303314",
                "listedAt": 1627012680,
                "tier": 1,
                "change": "-0.87",
                "rank": 10,
                "sparkline": [
                    "3276.2080062744353",
                    "3269.7783006947625",
                    "3260.671991580238",
                    "3260.9983574118055",
                    "3248.903112659861",
                    "3251.1911588808107",
                    "3235.4074902264456",
                    "3246.6683337668433",
                    "3242.698476057565",
                    "3215.21740312207",
                    "3228.2629751306063",
                    "3207.261277811195",
                    "3204.5101350998425",
                    "3210.243933803328",
                    "3210.524723334214",
                    "3217.624783677092",
                    "3206.830238958563",
                    "3195.973562774737",
                    "3202.5424726155616",
                    "3200.48274237851",
                    "3214.0402404636184",
                    "3243.204430080247",
                    "3246.331119132634",
                    null
                ],
                "lowVolume": false,
                "coinrankingUrl": "https://coinranking.com/coin/VINVMYf0u+lidostakedether-steth",
                "24hVolume": "36928582",
                "btcPrice": "0.030813629615425452",
                "contractAddresses": [
                    "ethereum/0xae7ab96520de3a18e5e111b5eaab095312d7fe84"
                ]
            },
            {
                "uuid": "qUhEFk1I61atv",
                "symbol": "TRX",
                "name": "TRON",
                "color": "#eb0029",
                "iconUrl": "https://cdn.coinranking.com/behejNqQs/trx.svg",
                "marketCap": "21573388570",
                "price": "0.24932475429479012",
                "listedAt": 1505260800,
                "tier": 1,
                "change": "-3.02",
                "rank": 11,
                "sparkline": [
                    "0.2571048015360889",
                    "0.2569913342421129",
                    "0.2566045467389842",
                    "0.2563741786252322",
                    "0.25517359878724577",
                    "0.25543155963351655",
                    "0.25391476736217383",
                    "0.25416907550121354",
                    "0.2536043983124771",
                    "0.2507891996588894",
                    "0.25132051845873576",
                    "0.2493555938353678",
                    "0.24849364316478462",
                    "0.2484069279068297",
                    "0.24693968865104107",
                    "0.24762907041614318",
                    "0.24788584147866166",
                    "0.2467002197732593",
                    "0.2454907829157812",
                    "0.2455025855673553",
                    "0.24542097877765823",
                    "0.24854872230372507",
                    "0.24945664078585914",
                    null
                ],
                "lowVolume": false,
                "coinrankingUrl": "https://coinranking.com/coin/qUhEFk1I61atv+tron-trx",
                "24hVolume": "1243124514",
                "btcPrice": "0.000002366460834793",
                "contractAddresses": []
            },
            {
                "uuid": "VLqpJwogdhHNb",
                "symbol": "LINK",
                "name": "Chainlink",
                "color": "#2c5cdc",
                "iconUrl": "https://cdn.coinranking.com/9NOP9tOem/chainlink.svg",
                "marketCap": "16246163835",
                "price": "25.46021718707746",
                "listedAt": 1505952000,
                "tier": 1,
                "change": "-0.28",
                "rank": 12,
                "sparkline": [
                    "25.50463925911285",
                    "25.477061877970616",
                    "25.463470004212414",
                    "25.454470796143855",
                    "25.394337390602093",
                    "25.498849622317884",
                    "25.336850221006955",
                    "25.21884654876207",
                    "24.980833918462928",
                    "24.639436696539228",
                    "24.825978680021265",
                    "24.673914212283567",
                    "24.679397091513042",
                    "24.619986208460496",
                    "24.46717827541566",
                    "24.458480538248224",
                    "24.296477951247955",
                    "24.170997350443628",
                    "24.23720838367454",
                    "24.37131530332168",
                    "24.372488958098284",
                    "25.047510806959632",
                    "25.416831402976076",
                    null
                ],
                "lowVolume": false,
                "coinrankingUrl": "https://coinranking.com/coin/VLqpJwogdhHNb+chainlink-link",
                "24hVolume": "801016734",
                "btcPrice": "0.000241655133638708",
                "contractAddresses": [
                    "avalanche-dfk/0x5947bb275c521040051d82396192181b413227a3",
                    "fantom/0xb3654dc3D10Ea7645f8319668E8F54d2574FBdC8",
                    "terra-classic/terra12dfv3f0e6m22z6cnhfn3nxk2en3z3zeqy6ctym",
                    "heco/0x9e004545c59d359f6b7bfb06a26390b087717b42",
                    "polygon/0x53E0bca35eC356BD5ddDFebbD1Fc0fD03FaBad39",
                    "sora/0x008484148dcf23d1b48908393e7a00d5fdc3bf81029a73eeca62a15ebfb1205a",
                    "solana/CWE8jPTUYhdCTZYWPTe1o5DFqfdjzWKc9WKz6rSjQUdG",
                    "bnb-smart-chain/0xf8a0bf9cf54bb92f17374d9e9a321e6a111a51bd",
                    "hoo-smart-chain/0x294cde734a863dcf65417992424405bccf3973e7",
                    "near/514910771af9ca656af840dff83e8264ecf986ca.factory.bridge.near",
                    "optimism/0x350a791bfc2c21f9ed5d10980dad2e2638ffa7f6",
                    "ethereum/0x514910771af9ca656af840dff83e8264ecf986ca",
                    "cronos/0xbc6f24649ccd67ec42342accdceccb2efa27c9d9",
                    "arbitrum/0x514910771af9ca656af840dff83e8264ecf986ca",
                    "arbitrum/0xf97f4df75117a78c1A5a0DBb814Af92458539FB4"
                ]
            },
            {
                "uuid": "x4WXHge-vvFY",
                "symbol": "WBTC",
                "name": "Wrapped BTC",
                "color": "#000000",
                "iconUrl": "https://cdn.coinranking.com/o3-8cvCHu/wbtc[1].svg",
                "marketCap": "15261666937",
                "price": "104805.53790812001",
                "listedAt": 1549894980,
                "tier": 1,
                "change": "0.76",
                "rank": 13,
                "sparkline": [
                    "103983.15473610717",
                    "104107.29613346829",
                    "104295.18992174546",
                    "104248.20560827029",
                    "103954.32219740908",
                    "103971.66294965915",
                    "103822.50288198094",
                    "103453.49758986218",
                    "103209.21548057048",
                    "102478.55538537471",
                    "102604.86044360242",
                    "102035.89006208991",
                    "102027.17983569119",
                    "102337.9557048502",
                    "102282.16695491465",
                    "102310.49109739371",
                    "102122.1999323741",
                    "101659.49472538629",
                    "101604.18303622828",
                    "101548.16365574316",
                    "101628.2636700011",
                    "102681.6871291614",
                    "104239.69698205081",
                    null
                ],
                "lowVolume": false,
                "coinrankingUrl": "https://coinranking.com/coin/x4WXHge-vvFY+wrappedbtc-wbtc",
                "24hVolume": "660867117",
                "btcPrice": "0.9947596315917625",
                "contractAddresses": [
                    "avalanche-dfk/0x50b7545627a5162F82A992c33b87aDc75187B218",
                    "fantom/0x321162Cd933E2Be498Cd2267a90534A804051b11",
                    "polygon/0x1bfd67037b42cf73acf2047067bd4f2c47d9bfd6",
                    "optimism/0x68f180fcce6836688e9084f035309e29bf0a2095",
                    "ethereum/0x2260fac5e5542a773aa44fbcfedf7c193bc2c599",
                    "cronos/0x062e66477faf219f25d27dced647bf57c3107d52",
                    "arbitrum/0x2f2a2543b76a4166549f7aab2e75bef0aefc5b0f",
                    "klaytn/0xdcbacf3f7a069922e677912998c8d57423c37dfa"
                ]
            },
            {
                "uuid": "dvUj0CzDZ",
                "symbol": "AVAX",
                "name": "Avalanche",
                "color": "#e84242",
                "iconUrl": "https://cdn.coinranking.com/S0C6Cw2-w/avax-avalanche.png",
                "marketCap": "14689032307",
                "price": "35.707588995450756",
                "listedAt": 1600961596,
                "tier": 1,
                "change": "-4.10",
                "rank": 14,
                "sparkline": [
                    "37.21110998644109",
                    "37.18577567424351",
                    "37.103491814608006",
                    "37.277268037915135",
                    "36.98055489944718",
                    "37.17284087228278",
                    "36.794414527926925",
                    "36.76174293090868",
                    "36.47800878677937",
                    "35.97021128409641",
                    "36.16892899726094",
                    "35.88902801845632",
                    "35.78790554050088",
                    "35.66789584837232",
                    "35.4766465265506",
                    "35.4410483208783",
                    "35.26587079886023",
                    "35.135504862124314",
                    "35.20501526050509",
                    "35.072662726921976",
                    "35.10806915707001",
                    "35.627252329127394",
                    "35.63523840408627",
                    null
                ],
                "lowVolume": false,
                "coinrankingUrl": "https://coinranking.com/coin/dvUj0CzDZ+avalanche-avax",
                "24hVolume": "279057300",
                "btcPrice": "0.000338917854753863",
                "contractAddresses": []
            },
            {
                "uuid": "CiixT63n3",
                "symbol": "wstETH",
                "name": "Wrapped liquid staked Ether 2.0",
                "color": "#70b9dc",
                "iconUrl": "https://cdn.coinranking.com/LQg69oxqx/wstETH.PNG",
                "marketCap": "13780612026",
                "price": "3861.526428662384",
                "listedAt": 1638756833,
                "tier": 1,
                "change": "-1.06",
                "rank": 15,
                "sparkline": [
                    "3901.4870778784484",
                    "3900.027721925385",
                    "3898.0353628142466",
                    "3905.6141029706755",
                    "3899.2083313259363",
                    "3887.92702133694",
                    "3863.965787725502",
                    "3864.029783961837",
                    "3864.2162229105456",
                    "3845.851091426733",
                    "3846.0637074751503",
                    "3846.8924536427644",
                    "3830.7757521153926",
                    "3831.497458372349",
                    "3825.882840591296",
                    "3845.7549344210056",
                    "3833.9069325172054",
                    "3820.9524257068615",
                    "3818.2274774922116",
                    "3816.3553687266835",
                    "3819.304788845982",
                    "3862.510194612826",
                    "3876.5582313122595",
                    null
                ],
                "lowVolume": false,
                "coinrankingUrl": "https://coinranking.com/coin/CiixT63n3+wrappedliquidstakedether20-wsteth",
                "24hVolume": "57382656",
                "btcPrice": "0.03665159956457259",
                "contractAddresses": [
                    "ethereum/0x7f39c581f595b53c5cb19bd0b3f8da6c935e2ca0",
                    "arbitrum/0x5979D7b546E38E414F7E9822514be443A4800529",
                    "polygon/0x03b54a6e9a984069379fae1a4fc4dbae93b3bccd",
                    "optimism/0x1f32b1c2345538c0c6f582fcb022739c4a194ebb"
                ]
            },
            {
                "uuid": "3xJluUMvp",
                "symbol": "SUI",
                "name": "Sui Network",
                "color": "#9fc5e8",
                "iconUrl": "https://cdn.coinranking.com/ofGxBKTzi/mVPQgClg_400x400.PNG",
                "marketCap": "13131772680",
                "price": "4.363339464749096",
                "listedAt": 1681785895,
                "tier": 1,
                "change": "-5.43",
                "rank": 16,
                "sparkline": [
                    "4.615711962268885",
                    "4.5861826632061735",
                    "4.567114589018524",
                    "4.5801478879615845",
                    "4.532360201825008",
                    "4.500111066886646",
                    "4.472102353418917",
                    "4.458483192262697",
                    "4.4267813241398555",
                    "4.351206786268146",
                    "4.398029400466966",
                    "4.3818335301540445",
                    "4.406018033533061",
                    "4.414832533585358",
                    "4.382183770730122",
                    "4.3838132810992905",
                    "4.357765291178516",
                    "4.329473232974992",
                    "4.322429181121671",
                    "4.314006056259129",
                    "4.306962076812565",
                    "4.386194085621151",
                    "4.3926387717421616",
                    null
                ],
                "lowVolume": false,
                "coinrankingUrl": "https://coinranking.com/coin/3xJluUMvp+suinetwork-sui",
                "24hVolume": "706540000",
                "btcPrice": "0.00004141454779106",
                "contractAddresses": []
            },
            {
                "uuid": "67YlI0K1b",
                "symbol": "TON",
                "name": "Toncoin",
                "color": "#0088cc",
                "iconUrl": "https://cdn.coinranking.com/1mf2KPPah/toncoin.png",
                "marketCap": "12760241694",
                "price": "5.127421767948291",
                "listedAt": 1640268459,
                "tier": 1,
                "change": "-3.93",
                "rank": 17,
                "sparkline": [
                    "5.34033904659176",
                    "5.314355049854075",
                    "5.286526704277213",
                    "5.316909620988285",
                    "5.2964981539971605",
                    "5.304571603091263",
                    "5.274000068565467",
                    "5.302524563846845",
                    "5.288871274171641",
                    "5.221664219663606",
                    "5.215617685833237",
                    "5.180009583454382",
                    "5.181672007328712",
                    "5.203651327860812",
                    "5.199911583645157",
                    "5.170196245128727",
                    "5.132772511644379",
                    "5.096472374710829",
                    "5.089832109640732",
                    "5.091034230204527",
                    "5.105782668968677",
                    "5.147552912049718",
                    "5.155207086710306",
                    null
                ],
                "lowVolume": false,
                "coinrankingUrl": "https://coinranking.com/coin/67YlI0K1b+toncoin-ton",
                "24hVolume": "166725443",
                "btcPrice": "0.000048666819432493",
                "contractAddresses": [
                    "bnb-smart-chain/0x76a797a59ba2c17726896976b7b3747bfd1d220f",
                    "ethereum/0x582d872a1b094fc48f5de31d3b73f2d9be47def1"
                ]
            },
            {
                "uuid": "jad286TjB",
                "symbol": "HBAR",
                "name": "Hedera",
                "color": "#000000",
                "iconUrl": "https://cdn.coinranking.com/dSCnSLilQ/hedera.svg",
                "marketCap": "12388717190",
                "price": "0.32383155213568865",
                "listedAt": 1568704980,
                "tier": 1,
                "change": "-0.75",
                "rank": 18,
                "sparkline": [
                    "0.3261134367408387",
                    "0.32566889811802735",
                    "0.3260237335172331",
                    "0.3283349177817337",
                    "0.3255564687277571",
                    "0.325846943518684",
                    "0.32497323813676365",
                    "0.32652300490830705",
                    "0.3240057541500628",
                    "0.3192880224819736",
                    "0.3196547932553819",
                    "0.3174326500867675",
                    "0.31846515517621216",
                    "0.3189707618886883",
                    "0.3176904330090404",
                    "0.3193475865768423",
                    "0.32027877309294983",
                    "0.31811115501892273",
                    "0.31748648282547987",
                    "0.3153499286155632",
                    "0.3154230536244031",
                    "0.3219951425771633",
                    "0.327004113197665",
                    null
                ],
                "lowVolume": false,
                "coinrankingUrl": "https://coinranking.com/coin/jad286TjB+hedera-hbar",
                "24hVolume": "475012211",
                "btcPrice": "0.000003073640591232",
                "contractAddresses": ["hedera/"]
            },
            {
                "uuid": "xz24e0BjL",
                "symbol": "SHIB",
                "name": "Shiba Inu",
                "color": "#fda32b",
                "iconUrl": "https://cdn.coinranking.com/fiZ4HfnRR/shib.png",
                "marketCap": "11867551607",
                "price": "0.000020130962057774",
                "listedAt": 1620650373,
                "tier": 1,
                "change": "-1.56",
                "rank": 19,
                "sparkline": [
                    "0.000020450889407242",
                    "0.000020357498907081",
                    "0.000020331472317781",
                    "0.000020466331815979",
                    "0.000020326742670422",
                    "0.00002035012392557",
                    "0.000020250789524733",
                    "0.000020203736883029",
                    "0.000020171309941707",
                    "0.000020007054177396",
                    "0.000020129594850331",
                    "0.000020033905145398",
                    "0.000020034285272187",
                    "0.000020065059830295",
                    "0.000020081242910689",
                    "0.000020091565073671",
                    "0.00002000682554813",
                    "0.00001992470201983",
                    "0.000019924435249287",
                    "0.000019825228322528",
                    "0.000019836350466148",
                    "0.000020103486864816",
                    "0.00002014706635158",
                    null
                ],
                "lowVolume": false,
                "coinrankingUrl": "https://coinranking.com/coin/xz24e0BjL+shibainu-shib",
                "24hVolume": "275644544",
                "btcPrice": "1.91072617e-10",
                "contractAddresses": [
                    "ethereum/0x95aD61b0a150d79219dCF64E1E6Cc01f0B64C4cE"
                ]
            },
            {
                "uuid": "_H5FVG9iW",
                "symbol": "UNI",
                "name": "Uniswap",
                "color": "#ff007a",
                "iconUrl": "https://cdn.coinranking.com/1heSvUgtl/uniswap-v2.svg?size=48x48",
                "marketCap": "11669696418",
                "price": "12.74797207152787",
                "listedAt": 1600323371,
                "tier": 1,
                "change": "-3.77",
                "rank": 20,
                "sparkline": [
                    "13.257332581109793",
                    "13.15292181681941",
                    "13.09521083341357",
                    "13.085873225191593",
                    "13.006390155631607",
                    "12.978315688540919",
                    "12.886973907863142",
                    "12.893126800131064",
                    "12.814624764852105",
                    "12.687650643392427",
                    "12.750205103955771",
                    "12.704807630865837",
                    "12.68908142778793",
                    "12.683893259477529",
                    "12.668556066811114",
                    "12.655188675345315",
                    "12.563198260340588",
                    "12.475014725667917",
                    "12.484350548099616",
                    "12.457069880137835",
                    "12.520772757320668",
                    "12.727134569200704",
                    "12.743233231274722",
                    null
                ],
                "lowVolume": false,
                "coinrankingUrl": "https://coinranking.com/coin/_H5FVG9iW+uniswap-uni",
                "24hVolume": "208746885",
                "btcPrice": "0.000120997117657393",
                "contractAddresses": [
                    "ethereum/0x1f9840a85d5aF5bf1D1762F925BDADdC4201F984",
                    "polygon/0xb33eaad8d922b1083446dc23f610c2567fb5180f",
                    "arbitrum/0xFa7F8980b0f1E64A2062791cc3b0871572f1F7f0",
                    "heco/0x22c54ce8321a4015740ee1109d9cbc25815c46e6",
                    "sora/0x009be848df92a400da2f217256c88d1a9b1a0304f9b3e90991a67418e1d3b08c",
                    "avalanche-c-chain/0x8eBAf22B6F053dFFeaf46f4Dd9eFA95D89ba8580",
                    "solana/8FU95xFJhUUkyyCLU13HSzDLs7oC4QZdXQHL6SCeab36",
                    "terra-classic/terra1wyxkuy5jq545fn7xfn3enpvs5zg9f9dghf6gxf",
                    "near/1f9840a85d5af5bf1d1762f925bdaddc4201f984.factory.bridge.near"
                ]
            },
            {
                "uuid": "Mtfb0obXVh59u",
                "symbol": "WETH",
                "name": "Wrapped Ether",
                "color": "#303030",
                "iconUrl": "https://cdn.coinranking.com/KIviQyZlt/weth.svg",
                "marketCap": "11567243277",
                "price": "3216.974893787758",
                "listedAt": 1600259445,
                "tier": 1,
                "change": "-1.99",
                "rank": 21,
                "sparkline": [
                    "3281.512673199628",
                    "3280.951337785802",
                    "3264.6284365256693",
                    "3261.847679519578",
                    "3261.5843880065113",
                    "3257.3627115184768",
                    "3245.604329771712",
                    "3254.50852345662",
                    "3251.935090594914",
                    "3233.31646115438",
                    "3230.599860721188",
                    "3224.0774388415566",
                    "3205.7817075198586",
                    "3207.6844118027025",
                    "3203.302404830414",
                    "3214.978637519787",
                    "3205.030355797507",
                    "3190.679735019188",
                    "3197.7292942248964",
                    "3192.008675124346",
                    "3195.901481309782",
                    "3224.662177789494",
                    "3227.763638726718",
                    null
                ],
                "lowVolume": false,
                "coinrankingUrl": "https://coinranking.com/coin/Mtfb0obXVh59u+wrappedether-weth",
                "24hVolume": "985417968",
                "btcPrice": "0.030533851779757183",
                "contractAddresses": [
                    "avalanche-dfk/0x49D5c2BdFfac6CE2BFdB6640F4F80f226bc10bAB",
                    "fantom/0x74b23882a30290451A17c44f4F05243b6b58C76d",
                    "cosmos-hub/ibc/EA1D43981D5C9A1C4AAEA9C23BB1D4FA126BA9BC7020A25E0AE4AA841EA25DC5",
                    "polygon/0x7ceb23fd6bc0add59e62ac25578270cff1b9f619",
                    "ethereum/0xc02aaa39b223fe8d0a0e5c4f27ead9083c756cc2",
                    "bnb-smart-chain/0x2170ed0880ac9a755fd29b2688956bd959f933f8",
                    "avalanche-c-chain/0x49D5c2BdFfac6CE2BFdB6640F4F80f226bc10bAB",
                    "kardiachain/0x1540020a94aa8bc189aa97639da213a4ca49d9a7",
                    "conflux/0xa47f43de2f9623acb395ca4905746496d2014d57",
                    "optimism/0x4200000000000000000000000000000000000006",
                    "cronos/0xe44fd7fcb2b1581822d0c862b68222998a0c299a",
                    "tron-trc-20/THb4CqiFdwNHsWsQCs4JhzwjMWys4aqCbF",
                    "klaytn/0xcd6f29dc9ca217d0973d3d21bf58edd3ca871a86",
                    "arbitrum/0x82af49447d8a07e3bd95bd0d56f35241523fbab1",
                    "base/0x4200000000000000000000000000000000000006"
                ]
            },
            {
                "uuid": "25W7FG7om",
                "symbol": "DOT",
                "name": "Polkadot",
                "color": "#E6007A",
                "iconUrl": "https://cdn.coinranking.com/V3NSSybv-/polkadot-dot.svg",
                "marketCap": "9720901997",
                "price": "6.382148047681736",
                "listedAt": 1598365200,
                "tier": 1,
                "change": "-2.95",
                "rank": 22,
                "sparkline": [
                    "6.571821802470774",
                    "6.545458163954192",
                    "6.527173594879675",
                    "6.5299171622596015",
                    "6.491137598039547",
                    "6.484860568186672",
                    "6.448110103390768",
                    "6.448581331006569",
                    "6.405686592329774",
                    "6.318958848903631",
                    "6.318709845972223",
                    "6.314393008398611",
                    "6.315787410819676",
                    "6.315430219567105",
                    "6.314345283727803",
                    "6.316119306360271",
                    "6.313227923534128",
                    "6.310568385513641",
                    "6.311774330095158",
                    "6.310461770379521",
                    "6.311108748489021",
                    "6.383889066607783",
                    "6.392412911317719",
                    null
                ],
                "lowVolume": false,
                "coinrankingUrl": "https://coinranking.com/coin/25W7FG7om+polkadot-dot",
                "24hVolume": "1071448384",
                "btcPrice": "0.000060576028398821",
                "contractAddresses": []
            },
            {
                "uuid": "D7B1x_ks7WhV5",
                "symbol": "LTC",
                "name": "Litecoin",
                "color": "#345d9d",
                "iconUrl": "https://cdn.coinranking.com/BUvPxmc9o/ltcnew.svg",
                "marketCap": "8695717154",
                "price": "115.48815771511738",
                "listedAt": 1382572800,
                "tier": 1,
                "change": "-1.11",
                "rank": 23,
                "sparkline": [
                    "116.87825418218945",
                    "116.90883016036206",
                    "117.21385001835844",
                    "117.6834499933191",
                    "116.14793081966205",
                    "115.92405834569615",
                    "115.09651328774827",
                    "115.2150243776584",
                    "115.10658133359478",
                    "113.93252913788038",
                    "114.41497116561236",
                    "113.63353831210425",
                    "113.47557912051428",
                    "113.59126500174683",
                    "113.100422356353",
                    "113.15968355865034",
                    "112.79028577016531",
                    "112.21163025560348",
                    "112.07718428971786",
                    "112.02116490185531",
                    "112.53982864198179",
                    "114.15102751788392",
                    "115.36874025791268",
                    null
                ],
                "lowVolume": false,
                "coinrankingUrl": "https://coinranking.com/coin/D7B1x_ks7WhV5+litecoin-ltc",
                "24hVolume": "902488053",
                "btcPrice": "0.001096153500234082",
                "contractAddresses": [
                    "cronos/0x9d97be214b68c7051215bb61059b4e299cd792c3"
                ]
            },
            {
                "uuid": "f3iaFeCKEmkaZ",
                "symbol": "XLM",
                "name": "Stellar",
                "color": "#000000",
                "iconUrl": "https://cdn.coinranking.com/78CxK1xsp/Stellar_symbol_black_RGB.svg",
                "marketCap": "8639882090",
                "price": "0.42760001054422747",
                "listedAt": 1484611200,
                "tier": 1,
                "change": "-1.38",
                "rank": 24,
                "sparkline": [
                    "0.4338359205991895",
                    "0.43279343103586226",
                    "0.43243569331637177",
                    "0.4365054954686684",
                    "0.4330232572539173",
                    "0.43304632601633053",
                    "0.42943328208673254",
                    "0.4283379768016938",
                    "0.426404874411953",
                    "0.4230036603578747",
                    "0.4238936223791897",
                    "0.4209538548160085",
                    "0.421356372451112",
                    "0.42176127178292094",
                    "0.42002396727192876",
                    "0.4215108759720819",
                    "0.419750070412673",
                    "0.4169416805189476",
                    "0.41699546198301984",
                    "0.4157009870522751",
                    "0.4157382832003489",
                    "0.42303486807816937",
                    "0.42643704341611716",
                    null
                ],
                "lowVolume": false,
                "coinrankingUrl": "https://coinranking.com/coin/f3iaFeCKEmkaZ+stellar-xlm",
                "24hVolume": "375803402",
                "btcPrice": "0.000004058556803845",
                "contractAddresses": ["stellar/"]
            },
            {
                "uuid": "q7gMmMdLb",
                "symbol": "BGB",
                "name": "Bitget Token",
                "color": "#040505",
                "iconUrl": "https://cdn.coinranking.com/rmrDoTpLt/bitget.png",
                "marketCap": "8626172872",
                "price": "7.188477393423376",
                "listedAt": 1651983014,
                "tier": 1,
                "change": "0.82",
                "rank": 25,
                "sparkline": [
                    "7.126000212042029",
                    "7.12644446058902",
                    "7.120483423736672",
                    "7.101015749585979",
                    "7.090873612885722",
                    "7.0921602126193095",
                    "7.076225021775579",
                    "7.065111100641729",
                    "7.083923372492409",
                    "7.042883400671101",
                    "7.0737840612487535",
                    "7.041322308640681",
                    "7.0307740017563916",
                    "7.059481241559147",
                    "7.054585614363354",
                    "7.097746529212051",
                    "7.122985628562362",
                    "7.067946893731179",
                    "7.065142515017829",
                    "7.124969387524368",
                    "7.166909945094431",
                    "7.1434821088135765",
                    "7.201438465593242",
                    null
                ],
                "lowVolume": false,
                "coinrankingUrl": "https://coinranking.com/coin/q7gMmMdLb+bitgettoken-bgb",
                "24hVolume": "194027349",
                "btcPrice": "0.000068229286985354",
                "contractAddresses": [
                    "ethereum/0x19de6b897Ed14A376Dda0Fe53a5420D2aC828a28"
                ]
            },
            {
                "uuid": "ZlZpzOJo43mIo",
                "symbol": "BCH",
                "name": "Bitcoin Cash",
                "color": "#8dc451",
                "iconUrl": "https://cdn.coinranking.com/By8ziihX7/bch.svg",
                "marketCap": "8409321450",
                "price": "439.55599147002977",
                "listedAt": 1541808000,
                "tier": 1,
                "change": "-0.84",
                "rank": 26,
                "sparkline": [
                    "443.40291788819627",
                    "443.0419672062476",
                    "441.4486055050308",
                    "440.679498616333",
                    "438.2667579501229",
                    "437.85832852915684",
                    "436.04446010139054",
                    "435.4294774940227",
                    "433.6899613544468",
                    "429.3941544721411",
                    "432.957372541104",
                    "430.7583785181007",
                    "431.39758263097434",
                    "431.4688040399989",
                    "430.30885496678775",
                    "430.96853885389",
                    "429.52647149476513",
                    "428.56360293304164",
                    "427.8824490771333",
                    "427.2884787162604",
                    "428.54340864728806",
                    "433.6780600785284",
                    "437.26618744874554",
                    null
                ],
                "lowVolume": false,
                "coinrankingUrl": "https://coinranking.com/coin/ZlZpzOJo43mIo+bitcoincash-bch",
                "24hVolume": "273853289",
                "btcPrice": "0.004172036753649463",
                "contractAddresses": []
            },
            {
                "uuid": "9T8gSchgx",
                "symbol": "TRUMP",
                "name": "OFFICIAL TRUMP",
                "color": "#e9dcbe",
                "iconUrl": "https://cdn.coinranking.com/fWaVFSsdS/35336.png",
                "marketCap": "7415481639",
                "price": "37.07740819731231",
                "listedAt": 1737294086,
                "tier": 1,
                "change": "-5.59",
                "rank": 27,
                "sparkline": [
                    "39.40425416819794",
                    "38.70711497533657",
                    "38.483957156400166",
                    "39.44523120466442",
                    "38.919361690583465",
                    "38.26134072308993",
                    "36.91004850402219",
                    "37.35411168806405",
                    "38.35153390255943",
                    "37.79434851414623",
                    "37.76155294722963",
                    "37.00441557812923",
                    "37.32671707648999",
                    "37.264532223332026",
                    "36.6855087977221",
                    "36.92332619653668",
                    "36.1564362588422",
                    "35.8814460116148",
                    "36.06583550132125",
                    "35.789195062160026",
                    "35.13309778595369",
                    "36.05882434225804",
                    "37.08170351281198",
                    null
                ],
                "lowVolume": false,
                "coinrankingUrl": "https://coinranking.com/coin/9T8gSchgx+officialtrump-trump",
                "24hVolume": "3633169281",
                "btcPrice": "0.000351919465849888",
                "contractAddresses": [
                    "solana/6p6xgHyF7AeE6TZkSmFsko444wqoP15icUSqi2jfGiPN"
                ]
            },
            {
                "uuid": "03WI8NQPF",
                "symbol": "PEPE",
                "name": "PEPE",
                "color": "#4f9842",
                "iconUrl": "https://cdn.coinranking.com/L9KYPBnG8/pepe_32.PNG",
                "marketCap": "6336845163",
                "price": "0.000015062983834479",
                "listedAt": 1681785707,
                "tier": 1,
                "change": "-3.19",
                "rank": 28,
                "sparkline": [
                    "0.000015581032753163",
                    "0.000015480353011009",
                    "0.000015390386989513",
                    "0.000015434926765275",
                    "0.000015297974243192",
                    "0.000015348036553884",
                    "0.000015135879849967",
                    "0.000015106278028155",
                    "0.000015012812901141",
                    "0.000014815511801897",
                    "0.000014886242258645",
                    "0.000014763493918003",
                    "0.000014795034009617",
                    "0.000014835136595837",
                    "0.000014951542227645",
                    "0.000014941565841989",
                    "0.000014849783746028",
                    "0.000014782463699792",
                    "0.000014837416078157",
                    "0.000014752815889764",
                    "0.000014725468994041",
                    "0.000015060209948718",
                    "0.0000151429174754",
                    null
                ],
                "lowVolume": false,
                "coinrankingUrl": "https://coinranking.com/coin/03WI8NQPF+pepe-pepe",
                "24hVolume": "926758205",
                "btcPrice": "1.42970005e-10",
                "contractAddresses": [
                    "ethereum/0x6982508145454Ce325dDbE47a25d4ec3d2311933",
                    "bnb-smart-chain/0x25d887Ce7a35172C62FeBFD67a1856F20FaEbB00"
                ]
            },
            {
                "uuid": "DCrsaMv68",
                "symbol": "NEAR",
                "name": "NEAR Protocol",
                "color": "#000000",
                "iconUrl": "https://cdn.coinranking.com/Cth83dCnl/near.png",
                "marketCap": "5891535001",
                "price": "5.011626898096628",
                "listedAt": 1615164591,
                "tier": 1,
                "change": "-4.10",
                "rank": 29,
                "sparkline": [
                    "5.230205529625723",
                    "5.219936921356173",
                    "5.18098784405269",
                    "5.185024226401004",
                    "5.1563299512793925",
                    "5.160229951742205",
                    "5.101676235837348",
                    "5.069341423457237",
                    "5.036356666615477",
                    "4.982717074139921",
                    "5.015763397102555",
                    "4.995860586515313",
                    "5.004781045108479",
                    "5.0042771670616135",
                    "4.997121642037345",
                    "4.999597907821437",
                    "4.964718047961792",
                    "4.929816254908063",
                    "4.926518158878625",
                    "4.906260715989108",
                    "4.913890916590524",
                    "4.998383355672395",
                    "5.014505791857566",
                    null
                ],
                "lowVolume": false,
                "coinrankingUrl": "https://coinranking.com/coin/DCrsaMv68+nearprotocol-near",
                "24hVolume": "209731288",
                "btcPrice": "0.000047567754780253",
                "contractAddresses": [
                    "ethereum/0x85f17cf997934a597031b2e18a9ab6ebd4b9f6a4"
                ]
            },
            {
                "uuid": "exbfr2U-0",
                "symbol": "USDE",
                "name": "USDe",
                "color": "#cecece",
                "iconUrl": "https://cdn.coinranking.com/qKumrPI5t/USDe.png",
                "marketCap": "5810875805",
                "price": "0.9995392129738572",
                "listedAt": 1712115684,
                "tier": 1,
                "change": "0.00",
                "rank": 30,
                "sparkline": [
                    "0.9994504076890942",
                    "0.9995181339652036",
                    "0.9993358342524195",
                    "0.9993066755556015",
                    "0.9988391668586866",
                    "0.9989248742769576",
                    "0.9989530453729312",
                    "0.9987747041211043",
                    "0.9987811756027255",
                    "0.9987971540816616",
                    "0.9993223827846104",
                    "0.9995620838454208",
                    "0.9995719805704548",
                    "0.9996745901613563",
                    "0.9996820692022913",
                    "0.9998160247498583",
                    "0.9997492648918854",
                    "0.9995189570550843",
                    "0.9993809357407714",
                    "0.999842791380545",
                    "0.9996136462286195",
                    "0.9998415827825601",
                    "0.9997102067758447",
                    null
                ],
                "lowVolume": false,
                "coinrankingUrl": "https://coinranking.com/coin/exbfr2U-0+usde-usde",
                "24hVolume": "106709440",
                "btcPrice": "0.000009487106111998",
                "contractAddresses": [
                    "ethereum/0x4c9edd5852cd905f086c759e8383e09bff1e68b3",
                    "arbitrum/0x5d3a1ff2b6bab83b63cd9ad0787074081a52ef34",
                    "bnb-smart-chain/0x5d3a1ff2b6bab83b63cd9ad0787074081a52ef34",
                    "optimism/0x5d3a1ff2b6bab83b63cd9ad0787074081a52ef34"
                ]
            },
            {
                "uuid": "MoTuySvg7",
                "symbol": "DAI",
                "name": "Dai",
                "color": "#ea9999",
                "iconUrl": "https://cdn.coinranking.com/mAZ_7LwOE/mutli-collateral-dai.svg",
                "marketCap": "5357107029",
                "price": "1.0017237518901905",
                "listedAt": 1585574040,
                "tier": 1,
                "change": "0.16",
                "rank": 31,
                "sparkline": [
                    "1.0002759360705975",
                    "1.0006211245988443",
                    "1.0008601930510683",
                    "1.0003853266419391",
                    "1.0003094250003426",
                    "1.0006302137980574",
                    "1.0003387777343606",
                    "1.0002170299232331",
                    "1.0007436899456228",
                    "1.0006873038010935",
                    "1.0007341399839327",
                    "1.0004885268782084",
                    "1.000484624617932",
                    "1.000355942367681",
                    "1.0005262063456248",
                    "1.0003464503429371",
                    "1.0007707164416662",
                    "1.0006465548222443",
                    "1.0002370125024387",
                    "0.9999880588087817",
                    "1.0004349064069047",
                    "1.0000876539851136",
                    "1.0011210520627352",
                    null
                ],
                "lowVolume": false,
                "coinrankingUrl": "https://coinranking.com/coin/MoTuySvg7+dai-dai",
                "24hVolume": "228009391",
                "btcPrice": "0.000009507840618695",
                "contractAddresses": [
                    "avalanche-dfk/0xd586E7F844cEa2F87f50152665BCbc2C279D8d70",
                    "fantom/0x8D11eC38a3EB5E956B052f67Da8Bdc9bef8Abf3E",
                    "polygon/0x8f3Cf7ad23Cd3CaDbD9735AFf958023239c6A063",
                    "ethereum/0x6B175474E89094C44Da98b954EedeAC495271d0F",
                    "bnb-smart-chain/0x1af3f329e8be154074d8769d1ffa4ee058b1dbc3",
                    "optimism/0xda10009cbd5d07dd0cecc66161fc93d7c9000da1"
                ]
            },
            {
                "uuid": "i5jggxiwp",
                "symbol": "BSC-USD",
                "name": "Binance-Peg BSC-USD",
                "color": "#2a9e7c",
                "iconUrl": "https://cdn.coinranking.com/SeA5fxqOR/busdt_32.png",
                "marketCap": "5164171510",
                "price": "0.9959938754187294",
                "listedAt": 1717062261,
                "tier": 1,
                "change": "-0.41",
                "rank": 32,
                "sparkline": [
                    "0.9965197353718432",
                    "0.9972516015666603",
                    "1.0299351741820102",
                    "1.0222890209270392",
                    "1.007940493564944",
                    "1.0044848407286244",
                    "1.0038433424141897",
                    "0.9978743432188975",
                    "0.996132175502928",
                    "0.9930831544774571",
                    "0.9904113574186891",
                    "1.0036587011943774",
                    "1.017347450798592",
                    "1.0036485476230856",
                    "0.9994290150151653",
                    "0.9984754517655058",
                    "0.9967136193415922",
                    "0.9976531517319247",
                    "0.9964836496441072",
                    "0.9917998824633727",
                    "0.9986789404882329",
                    "0.9992277355563887",
                    "0.9929253917260082",
                    null
                ],
                "lowVolume": false,
                "coinrankingUrl": "https://coinranking.com/coin/i5jggxiwp+binance-pegbsc-usd-bsc-usd",
                "24hVolume": "51035678",
                "btcPrice": "0.000009456827381292",
                "contractAddresses": [
                    "bnb-smart-chain/0x55d398326f99059ff775485246999027b3197955"
                ]
            },
            {
                "uuid": "ixgUfzmLR",
                "symbol": "AAVE",
                "name": "Aave",
                "color": "#e5e4fc",
                "iconUrl": "https://cdn.coinranking.com/A_PrSs460/aave.png",
                "marketCap": "5087494576",
                "price": "335.18106513277667",
                "listedAt": 1603447311,
                "tier": 1,
                "change": "-4.95",
                "rank": 33,
                "sparkline": [
                    "352.76956747208914",
                    "351.39810216069185",
                    "350.9987139204199",
                    "352.45174345300074",
                    "350.10431194584834",
                    "350.66500219525193",
                    "347.62574985648445",
                    "347.6478434407959",
                    "341.67331506705096",
                    "337.1392671380325",
                    "338.4633632618136",
                    "335.1419928061402",
                    "335.8241738234175",
                    "335.74367094805143",
                    "335.16800286770956",
                    "337.27654500821126",
                    "334.92815659144213",
                    "333.0572913167058",
                    "334.5715168561173",
                    "333.2396505439299",
                    "333.54098614165366",
                    "340.0222864201774",
                    "338.64210521971944",
                    null
                ],
                "lowVolume": false,
                "coinrankingUrl": "https://coinranking.com/coin/ixgUfzmLR+aave-aave",
                "24hVolume": "385922838",
                "btcPrice": "0.0031813642630251",
                "contractAddresses": [
                    "avalanche-dfk/0x63a72806098Bd3D9520cC43356dD78afe5D386D9",
                    "fantom/0x6a07A792ab2965C72a5B8088d3a069A7aC3a993B",
                    "avalanche-c-chain/0x8ce2dee54bb9921a2ae0a63dbb2df8ed88b91dd9",
                    "heco/0x202b4936fe1a82a4965220860ae46d7d3939bb25",
                    "polygon/0xd6df932a45c0f255f85145f286ea0b292b21c90b",
                    "ethereum/0x7fc66500c84a76ad7e9c93437bfc5ac33e2ddae9",
                    "bnb-smart-chain/0xfb6115445bff7b52feb98650c87f44907e58f802"
                ]
            },
            {
                "uuid": "HGYj5JCv5",
                "symbol": "APT",
                "name": "Aptos",
                "color": "#000000",
                "iconUrl": "https://cdn.coinranking.com/KXUaDFjqm/21794.png",
                "marketCap": "4800343381",
                "price": "8.386128017196977",
                "listedAt": 1666148370,
                "tier": 1,
                "change": "-2.65",
                "rank": 34,
                "sparkline": [
                    "8.62018700509586",
                    "8.599794955723812",
                    "8.576680658843932",
                    "8.583225451962848",
                    "8.544360046879817",
                    "8.54059161217013",
                    "8.487760505076132",
                    "8.477640760320709",
                    "8.426434512421865",
                    "8.322851186613704",
                    "8.372808465862922",
                    "8.326785918039432",
                    "8.343481882973709",
                    "8.350964142233165",
                    "8.339248446835063",
                    "8.353806871139563",
                    "8.315527299860626",
                    "8.26538500668066",
                    "8.277201016204593",
                    "8.252354309879172",
                    "8.264682359575842",
                    "8.371477850240538",
                    "8.405953528242119",
                    null
                ],
                "lowVolume": false,
                "coinrankingUrl": "https://coinranking.com/coin/HGYj5JCv5+aptos-apt",
                "24hVolume": "129890375",
                "btcPrice": "0.000079596763523904",
                "contractAddresses": []
            },
            {
                "uuid": "aMNLwaUbY",
                "symbol": "ICP",
                "name": "Internet Computer (DFINITY)",
                "color": "#00042b",
                "iconUrl": "https://cdn.coinranking.com/1uJ_RVrmC/dfinity-icp.png",
                "marketCap": "4460499133",
                "price": "9.292125524885758",
                "listedAt": 1601555742,
                "tier": 1,
                "change": "-0.95",
                "rank": 35,
                "sparkline": [
                    "9.363722726890012",
                    "9.2994503828592",
                    "9.23381072285903",
                    "9.227407489384984",
                    "9.134821669226879",
                    "9.10863729709719",
                    "9.071901379912887",
                    "9.158822435046671",
                    "9.122331198997212",
                    "9.047711841656492",
                    "9.126564777270515",
                    "9.074557460398458",
                    "9.081216493699849",
                    "9.111876431896402",
                    "9.144625749456917",
                    "9.204258860626318",
                    "9.155713531519847",
                    "9.068645408942075",
                    "9.060471285083484",
                    "9.038006664149632",
                    "9.05729102111479",
                    "9.229801590057088",
                    "9.258936000581851",
                    null
                ],
                "lowVolume": false,
                "coinrankingUrl": "https://coinranking.com/coin/aMNLwaUbY+internetcomputerdfinity-icp",
                "24hVolume": "167147971",
                "btcPrice": "0.000088196020442576",
                "contractAddresses": []
            },
            {
                "uuid": "hnfQfsYfeIGUQ",
                "symbol": "ETC",
                "name": "Ethereum Classic",
                "color": "#699070",
                "iconUrl": "https://cdn.coinranking.com/rJfyor__W/etc.svg",
                "marketCap": "4270387898",
                "price": "28.409804096070754",
                "listedAt": 1469577600,
                "tier": 1,
                "change": "5.69",
                "rank": 36,
                "sparkline": [
                    "26.904121280320734",
                    "26.884438636416753",
                    "26.892136596699924",
                    "26.8543091767513",
                    "26.84906752762224",
                    "26.860320744641246",
                    "26.84515050189692",
                    "26.926355608520886",
                    "26.899917772918098",
                    "26.83661253529896",
                    "27.28498571893294",
                    "27.072611818350957",
                    "27.001802934170644",
                    "26.849256799717498",
                    "26.879478740618616",
                    "26.98785232823377",
                    "26.849351508793468",
                    "26.819098416920795",
                    "26.957815147027503",
                    "27.00855947438607",
                    "27.33475494932593",
                    "27.653036716626875",
                    "28.03081466508549",
                    null
                ],
                "lowVolume": false,
                "coinrankingUrl": "https://coinranking.com/coin/hnfQfsYfeIGUQ+ethereumclassic-etc",
                "24hVolume": "609196933",
                "btcPrice": "0.000269651077798742",
                "contractAddresses": []
            },
            {
                "uuid": "BoI4ux0nd",
                "symbol": "MNT",
                "name": "Mantle",
                "color": "#000000",
                "iconUrl": "https://cdn.coinranking.com/lXjHdEmpI/bLhE1aY1_400x400.PNG",
                "marketCap": "4102624424",
                "price": "1.2193156220411927",
                "listedAt": 1689647196,
                "tier": 1,
                "change": "5.56",
                "rank": 37,
                "sparkline": [
                    "1.155857517877812",
                    "1.1472286443588489",
                    "1.136296974087289",
                    "1.1350940806253238",
                    "1.1261476932448315",
                    "1.1235980152915468",
                    "1.1069841738648825",
                    "1.0987529076334286",
                    "1.0840096295377208",
                    "1.074003026539243",
                    "1.0803462186817814",
                    "1.074992986841709",
                    "1.0820677719835985",
                    "1.1060130050388723",
                    "1.1040702613833078",
                    "1.1335152570404103",
                    "1.1410329097730623",
                    "1.149594811079759",
                    "1.150895994558163",
                    "1.1661141313855634",
                    "1.1744225912790998",
                    "1.186032218400922",
                    "1.1833431503834784",
                    null
                ],
                "lowVolume": false,
                "coinrankingUrl": "https://coinranking.com/coin/BoI4ux0nd+mantle-mnt",
                "24hVolume": "164486359",
                "btcPrice": "0.000011573109428999",
                "contractAddresses": [
                    "ethereum/0x3c3a81e81dc49a522a592e7622a7e711c06bf354"
                ]
            },
            {
                "uuid": "3mVx2FX_iJFp5",
                "symbol": "XMR",
                "name": "Monero",
                "color": "#ff7519",
                "iconUrl": "https://cdn.coinranking.com/Syz-oSd_Z/xmr.svg",
                "marketCap": "4016215630",
                "price": "217.71948554185502",
                "listedAt": 1422489600,
                "tier": 1,
                "change": "1.70",
                "rank": 38,
                "sparkline": [
                    "214.87657311572514",
                    "218.6389024851179",
                    "221.56019249746637",
                    "220.04658861303813",
                    "220.76647109995034",
                    "223.01037195141797",
                    "222.55434625145224",
                    "223.4318346768576",
                    "224.07047677560456",
                    "223.33266109220398",
                    "224.0698238852442",
                    "225.19062023058862",
                    "226.02386610393947",
                    "225.53131565741788",
                    "222.67926395334584",
                    "221.5697489690116",
                    "220.87920535496752",
                    "218.44350670652148",
                    "218.88306060129867",
                    "218.6333855847205",
                    "216.25039876439615",
                    "219.10226957866027",
                    "218.37773542076607",
                    null
                ],
                "lowVolume": false,
                "coinrankingUrl": "https://coinranking.com/coin/3mVx2FX_iJFp5+monero-xmr",
                "24hVolume": "64071471",
                "btcPrice": "0.002066480069190923",
                "contractAddresses": ["monero/"]
            },
            {
                "uuid": "FEbS54wxo4oIl",
                "symbol": "VET",
                "name": "VeChain",
                "color": "#4bc0fa",
                "iconUrl": "https://cdn.coinranking.com/B1_TDu9Dm/VEN.svg",
                "marketCap": "4011016410",
                "price": "0.04952786776465332",
                "listedAt": 1533427200,
                "tier": 1,
                "change": "2.43",
                "rank": 39,
                "sparkline": [
                    "0.04837989241083475",
                    "0.04811776198836517",
                    "0.04806986589612784",
                    "0.048171258924075144",
                    "0.04802688760376204",
                    "0.04822369022756255",
                    "0.047897550985546516",
                    "0.048043697483769146",
                    "0.04802413433304751",
                    "0.04758099736661862",
                    "0.047931481472723476",
                    "0.047484262347711435",
                    "0.047417274584665596",
                    "0.04730612857270711",
                    "0.047397668673675605",
                    "0.04780435311394442",
                    "0.04734471335935254",
                    "0.047007480268739625",
                    "0.047009251443709675",
                    "0.04688758251129116",
                    "0.046981079976873896",
                    "0.04804013130845788",
                    "0.048336812064358636",
                    null
                ],
                "lowVolume": false,
                "coinrankingUrl": "https://coinranking.com/coin/FEbS54wxo4oIl+vechain-vet",
                "24hVolume": "105832988",
                "btcPrice": "4.70092749624e-7",
                "contractAddresses": ["vechain/"]
            },
            {
                "uuid": "65PHZTpmE55b",
                "symbol": "CRO",
                "name": "Cronos",
                "color": "#01275d",
                "iconUrl": "https://cdn.coinranking.com/2o91jm73M/cro.svg",
                "marketCap": "3847336936",
                "price": "0.14120737434518646",
                "listedAt": 1548953220,
                "tier": 1,
                "change": "-0.17",
                "rank": 40,
                "sparkline": [
                    "0.14161332871946886",
                    "0.14194366687312754",
                    "0.14173592137836383",
                    "0.1423103951946037",
                    "0.14109222496179977",
                    "0.14141708478883835",
                    "0.1406398468624931",
                    "0.13979042452362392",
                    "0.13864872449490967",
                    "0.13707805693105765",
                    "0.1377840507268613",
                    "0.13660219170946947",
                    "0.13681240337044234",
                    "0.13680348746610382",
                    "0.13626519526315836",
                    "0.13522597901172873",
                    "0.13431559621189013",
                    "0.13363857826648712",
                    "0.13341056772851023",
                    "0.13256999445432557",
                    "0.13313989687429637",
                    "0.1367746190494977",
                    "0.1395030001870038",
                    null
                ],
                "lowVolume": false,
                "coinrankingUrl": "https://coinranking.com/coin/65PHZTpmE55b+cronos-cro",
                "24hVolume": "32830533",
                "btcPrice": "0.000001340266921819",
                "contractAddresses": [
                    "ethereum/0xa0b73e1ff0b80914ab6fe0444e65848c4c34450b",
                    "polygon/0xada58df0f643d959c2a47c9d4d4c1a4defe3f11c"
                ]
            },
            {
                "uuid": "iDZ0tG-wI",
                "symbol": "POL",
                "name": "Polygon Ecosystem Token",
                "color": "#8837da",
                "iconUrl": "https://cdn.coinranking.com/Txu2op7mz/poly.png",
                "marketCap": "3719241477",
                "price": "0.4405061408832486",
                "listedAt": 1698634569,
                "tier": 1,
                "change": "-1.92",
                "rank": 41,
                "sparkline": [
                    "0.44884774234266683",
                    "0.4466657917948894",
                    "0.4451689108169554",
                    "0.44663553494290537",
                    "0.4450711720513553",
                    "0.44575225744522073",
                    "0.44212184268447763",
                    "0.44138999640952564",
                    "0.43923023991495236",
                    "0.4351719170537242",
                    "0.43892940323165275",
                    "0.4361034667311586",
                    "0.4360868246306531",
                    "0.43615567631835084",
                    "0.4361705102160242",
                    "0.43732791143687744",
                    "0.4357252338178711",
                    "0.4336282561675346",
                    "0.4330131483103243",
                    "0.4315705738644081",
                    "0.43309259907218073",
                    "0.43817155893133886",
                    "0.439613337385329",
                    null
                ],
                "lowVolume": false,
                "coinrankingUrl": "https://coinranking.com/coin/iDZ0tG-wI+polygonecosystemtoken-pol",
                "24hVolume": "147211718",
                "btcPrice": "0.000004181055077482",
                "contractAddresses": [
                    "ethereum/0x455e53cbb86018ac2b8092fdcd39d8444affc3f6"
                ]
            },
            {
                "uuid": "vfo5XYwcV",
                "symbol": "RENDER",
                "name": "Render Token",
                "color": "#f9dddd",
                "iconUrl": "https://cdn.coinranking.com/qjrWSgiUG/RENDER.png",
                "marketCap": "3614062126",
                "price": "6.981123299326473",
                "listedAt": 1710916148,
                "tier": 1,
                "change": "-3.08",
                "rank": 42,
                "sparkline": [
                    "7.21018596876805",
                    "7.193597894729352",
                    "7.15507127205985",
                    "7.206120389688291",
                    "7.1100524149097835",
                    "7.09647890021016",
                    "7.045301696901241",
                    "7.038055416321926",
                    "7.000524927245752",
                    "6.910615177787757",
                    "6.940838858562949",
                    "6.883157591822689",
                    "6.90776891388882",
                    "6.91723055805046",
                    "6.927814391274123",
                    "6.9331605420173466",
                    "6.882567547046348",
                    "6.82824871471761",
                    "6.845211590759595",
                    "6.802786102793692",
                    "6.791786141618928",
                    "6.882587428014856",
                    "6.927097537364983",
                    null
                ],
                "lowVolume": false,
                "coinrankingUrl": "https://coinranking.com/coin/vfo5XYwcV+rendertoken-render",
                "24hVolume": "116271309",
                "btcPrice": "0.000066261189818259",
                "contractAddresses": [
                    "solana/rndrizKT3MK1iimdxRdWabcF7Zg7AR5T4nud4EkHBof"
                ]
            },
            {
                "uuid": "TpHE2IShQw-sJ",
                "symbol": "ALGO",
                "name": "Algorand",
                "color": null,
                "iconUrl": "https://cdn.coinranking.com/lzbmCkUGB/algo.svg",
                "marketCap": "3433400638",
                "price": "0.4093776300923604",
                "listedAt": 1562082540,
                "tier": 1,
                "change": "-2.09",
                "rank": 43,
                "sparkline": [
                    "0.41752608255040113",
                    "0.41504512030695934",
                    "0.41340306679496225",
                    "0.41405165997990406",
                    "0.4092290254774918",
                    "0.4096558263192597",
                    "0.405754836329527",
                    "0.4047620969398067",
                    "0.4024114401035616",
                    "0.3978113388552372",
                    "0.3991085036379012",
                    "0.39580537737974786",
                    "0.39629655113261025",
                    "0.39771069275659593",
                    "0.39712186865786603",
                    "0.39703963971524586",
                    "0.3951230338762501",
                    "0.3925970294747077",
                    "0.3933086099055395",
                    "0.3936206766393346",
                    "0.39385133256175364",
                    "0.4045331737739016",
                    "0.4104758496302139",
                    null
                ],
                "lowVolume": false,
                "coinrankingUrl": "https://coinranking.com/coin/TpHE2IShQw-sJ+algorand-algo",
                "24hVolume": "189182350",
                "btcPrice": "0.00000388559945038",
                "contractAddresses": []
            },
            {
                "uuid": "PDKcptVnzJTmN",
                "symbol": "OKB",
                "name": "OKB",
                "color": "#2d60e0",
                "iconUrl": "https://cdn.coinranking.com/xcZdYtX6E/okx.png",
                "marketCap": "3380069580",
                "price": "56.334493002092586",
                "listedAt": 1538524800,
                "tier": 1,
                "change": "-1.22",
                "rank": 44,
                "sparkline": [
                    "57.00949488590121",
                    "57.1946859073758",
                    "56.80751193736384",
                    "56.81665940900636",
                    "56.63205352740025",
                    "56.41728670404383",
                    "55.587897064306006",
                    "55.29375069372405",
                    "55.0704934100443",
                    "54.78580632481887",
                    "54.3718807937909",
                    "53.71943726134318",
                    "53.86475055314588",
                    "53.68205490870008",
                    "53.7681701068511",
                    "53.64277995862612",
                    "53.493465716247805",
                    "53.200826419618274",
                    "53.01786069202092",
                    "52.85710518463306",
                    "52.87117632090914",
                    "54.03352825372501",
                    "54.18108425015205",
                    null
                ],
                "lowVolume": false,
                "coinrankingUrl": "https://coinranking.com/coin/PDKcptVnzJTmN+okb-okb",
                "24hVolume": "19964457",
                "btcPrice": "0.000534697694637075",
                "contractAddresses": [
                    "ethereum/0x75231f58b43240c9718dd58b4967c5114342a86c"
                ]
            },
            {
                "uuid": "AWma-WzFHmKVQ",
                "symbol": "FET",
                "name": "Artificial Superintelligence Alliance",
                "color": "#054700",
                "iconUrl": "https://cdn.coinranking.com/8w7heKkw8/yrtftru.png",
                "marketCap": "3374179362",
                "price": "1.2407379791350601",
                "listedAt": 1553179080,
                "tier": 1,
                "change": "-4.92",
                "rank": 45,
                "sparkline": [
                    "1.306840739663222",
                    "1.3069170344947556",
                    "1.300537064075263",
                    "1.3012384221111275",
                    "1.2931695292794239",
                    "1.2915508129209305",
                    "1.2786519374623497",
                    "1.275667783604211",
                    "1.2704074599659103",
                    "1.253349169380083",
                    "1.2631116952655184",
                    "1.250901450194487",
                    "1.2366684043327185",
                    "1.2362442080491443",
                    "1.2337897157400826",
                    "1.2402286978118884",
                    "1.2319471062437586",
                    "1.2242299192792003",
                    "1.220787108825424",
                    "1.2109017628693413",
                    "1.2035820358856615",
                    "1.222661922769865",
                    "1.2252465610988708",
                    null
                ],
                "lowVolume": false,
                "coinrankingUrl": "https://coinranking.com/coin/AWma-WzFHmKVQ+artificialsuperintelligencealliance-fet",
                "24hVolume": "177737608",
                "btcPrice": "0.000011776439295682",
                "contractAddresses": [
                    "ethereum/0xaea46a60368a7bd060eec7df8cba43b7ef41ad85",
                    "bnb-smart-chain/0x031b41e504677879370e9dbcf937283a8691fa7f"
                ]
            },
            {
                "uuid": "V8GxkwWow",
                "symbol": "KAS",
                "name": "Kaspa",
                "color": "#74ccbc",
                "iconUrl": "https://cdn.coinranking.com/8JltIp1eX/kaspa.png",
                "marketCap": "3373373322",
                "price": "0.13192663403590724",
                "listedAt": 1665132341,
                "tier": 1,
                "change": "0.63",
                "rank": 46,
                "sparkline": [
                    "0.13098980152879455",
                    "0.13206360631291997",
                    "0.1324530209974795",
                    "0.13356434946467882",
                    "0.13191503643834612",
                    "0.13147627122074798",
                    "0.13041366530625428",
                    "0.13047442474355772",
                    "0.13071705371166378",
                    "0.12942193061164226",
                    "0.12893936812389958",
                    "0.12714277687681733",
                    "0.12817913142155216",
                    "0.1292760080117523",
                    "0.12895110247091365",
                    "0.12949846211323945",
                    "0.12875580767769187",
                    "0.12782450673103254",
                    "0.12689274217115032",
                    "0.12782721854955764",
                    "0.12806866501182948",
                    "0.13039943110814387",
                    "0.1316916371684937",
                    null
                ],
                "lowVolume": false,
                "coinrankingUrl": "https://coinranking.com/coin/V8GxkwWow+kaspa-kas",
                "24hVolume": "61546502",
                "btcPrice": "0.000001252178963918",
                "contractAddresses": []
            },
            {
                "uuid": "cTdD8lD-6",
                "symbol": "OM",
                "name": "Mantra DAO",
                "color": "#000000",
                "iconUrl": "https://cdn.coinranking.com/ljdgopkOU/6536.png",
                "marketCap": "3314090832",
                "price": "3.6165618310793586",
                "listedAt": 1626942731,
                "tier": 1,
                "change": "2.33",
                "rank": 47,
                "sparkline": [
                    "3.5347066333748676",
                    "3.530040572054504",
                    "3.5977652029616265",
                    "3.6886293931260763",
                    "3.7102013234936555",
                    "3.705698118259581",
                    "3.6820725283842175",
                    "3.698216027079348",
                    "3.702613261189542",
                    "3.6529786347858395",
                    "3.65612725492781",
                    "3.619297945238203",
                    "3.611014234984118",
                    "3.615551553858331",
                    "3.6073054332177685",
                    "3.624364488288174",
                    "3.616026601319706",
                    "3.5940157919898414",
                    "3.5764152393169977",
                    "3.563847900626006",
                    "3.564640791319811",
                    "3.6068912967356193",
                    "3.602900296365415",
                    null
                ],
                "lowVolume": false,
                "coinrankingUrl": "https://coinranking.com/coin/cTdD8lD-6+mantradao-om",
                "24hVolume": "76231244",
                "btcPrice": "0.000034326523068535",
                "contractAddresses": [
                    "polygon/0xc3ec80343d2bae2f8e680fdadde7c17e71e114ea",
                    "bnb-smart-chain/0xf78d2e7936f5fe18308a3b2951a93b6c4a41f5e2",
                    "ethereum/0x3593d125a4f7849a1b059e64f4517a86dd60c95d",
                    "base/0x3992b27da26848c2b19cea6fd25ad5568b68ab98"
                ]
            },
            {
                "uuid": "7AQlxzQpQ",
                "symbol": "ONDO",
                "name": "ONDO",
                "color": "#040404",
                "iconUrl": "https://cdn.coinranking.com/ntSfLv-Es/ONDO.png",
                "marketCap": "3214920602",
                "price": "1.3748545901638647",
                "listedAt": 1701755988,
                "tier": 1,
                "change": "4.74",
                "rank": 48,
                "sparkline": [
                    "1.3146836586959558",
                    "1.3105979498862608",
                    "1.313217317939172",
                    "1.31779862572016",
                    "1.3055496608635833",
                    "1.3024702655966451",
                    "1.291637676762799",
                    "1.2897965439238745",
                    "1.2819064502515358",
                    "1.268496461661565",
                    "1.2831897629064513",
                    "1.2724905537508782",
                    "1.2754265317406555",
                    "1.280815102136466",
                    "1.2748753809625157",
                    "1.2764818618571103",
                    "1.2701108949018043",
                    "1.2596500742541032",
                    "1.258046233353151",
                    "1.2756471884597702",
                    "1.3182040498192418",
                    "1.3569968202813172",
                    "1.3481094048514206",
                    null
                ],
                "lowVolume": false,
                "coinrankingUrl": "https://coinranking.com/coin/7AQlxzQpQ+ondo-ondo",
                "24hVolume": "387299584",
                "btcPrice": "0.00001304940438169",
                "contractAddresses": [
                    "ethereum/0xfAbA6f8e4a5E8Ab82F62fe7C39859FA577269BE3"
                ]
            },
            {
                "uuid": "pgv7xSFi6",
                "symbol": "TAO",
                "name": "Bittensor",
                "color": "#000000",
                "iconUrl": "https://cdn.coinranking.com/q1VmAQpFI/ARUsPeNQ_400x400.png",
                "marketCap": "3169335763",
                "price": "385.78773712406155",
                "listedAt": 1679499254,
                "tier": 1,
                "change": "-6.05",
                "rank": 49,
                "sparkline": [
                    "411.09543096532354",
                    "410.78326029084866",
                    "409.5180569425839",
                    "411.65980383307186",
                    "407.23817978066836",
                    "405.20274863244714",
                    "400.125996488817",
                    "396.885435333823",
                    "393.43316290361867",
                    "390.5866195714258",
                    "393.3750755825496",
                    "390.1036685173475",
                    "389.5980540633208",
                    "388.7920150706519",
                    "388.71392718537743",
                    "391.65170359893875",
                    "389.3174538165737",
                    "383.06842655605936",
                    "380.59859096359327",
                    "378.32765238388123",
                    "380.2107491645069",
                    "387.4743472416746",
                    "385.09510032540646",
                    null
                ],
                "lowVolume": false,
                "coinrankingUrl": "https://coinranking.com/coin/pgv7xSFi6+bittensor-tao",
                "24hVolume": "155926395",
                "btcPrice": "0.00366169646102659",
                "contractAddresses": []
            },
            {
                "uuid": "oCZEPpH_b",
                "symbol": "MORPHO",
                "name": "Morpho Token",
                "color": "#dce9fb",
                "iconUrl": "https://cdn.coinranking.com/3ovBRaxuv/MORPHO.png",
                "marketCap": "3163925305",
                "price": "3.2650254819166475",
                "listedAt": 1732231953,
                "tier": 1,
                "change": "-3.05",
                "rank": 50,
                "sparkline": [
                    "3.3799764370112113",
                    "3.4206680652453207",
                    "3.4918128195095886",
                    "3.460369825055953",
                    "3.4639183982261263",
                    "3.400364591233886",
                    "3.3359600497162427",
                    "3.3179343349665205",
                    "3.2708396771021735",
                    "3.2244619535254695",
                    "3.231353242471155",
                    "3.1932506398994733",
                    "3.18905135582608",
                    "3.1879188707357997",
                    "3.160454961254289",
                    "3.162642579284035",
                    "3.1853503215545986",
                    "3.1947996566885886",
                    "3.2401881984868366",
                    "3.262785210265471",
                    "3.2461881124349103",
                    "3.287322686007516",
                    "3.3087877833868946",
                    null
                ],
                "lowVolume": false,
                "coinrankingUrl": "https://coinranking.com/coin/oCZEPpH_b+morphotoken-morpho",
                "24hVolume": "48303889",
                "btcPrice": "0.000030989922959763",
                "contractAddresses": [
                    "ethereum/0x58D97B57BB95320F9a05dC918Aef65434969c2B2"
                ]
            }
        ]
    }
}
